{"availability":1,"classification":2,"computation_units":"per 100000 population","customisation":"Alternative national","data_non_statistical":false,"data_show_map":false,"goal_meta_link":"http://unstats.un.org/sdgs/files/metadata-compilation/Metadata-Goal-3.pdf","goal_meta_link_text":"United Nations Sustainable Development Goals Metadata (pdf 865kB)","graph_title":"Coverage of treatment interventions (pharmacological, psychosocial and rehabilitation and aftercare services) for substance use disorders","graph_type":"line","indicator_number":"3.5.1","indicator_name":"Coverage of treatment interventions (pharmacological, psychosocial and rehabilitation and aftercare services) for substance use disorders","indicator_sort_order":"03-05-01","layout":"indicator","national_geographical_coverage":"Kazakhstan","permalink":"/3-5-1/","published":true,"reporting_status":"complete","sdg_goal":"3","source_active_1":true,"source_compilation_1":"Ministry of Healthcare of the Republic of Kazakhstan","source_data_1":"Administrative data","source_implementation_1":"Ministry of Healthcare of the Republic of Kazakhstan","tags":[],"target_name":"Strengthen the prevention and treatment of substance abuse, including narcotic drug abuse and harmful use of alcohol","target_id":"3.5","un_custodian_agency":"WHO,UNODC","un_designated_tier":"3","page_content":"","national_metadata_update_url_text":"2020-08-31: see changes on GitHub","national_metadata_update_url":"https://github.com/brockfanning/sdg-data-kazstat-upgrade/commit/ff4a5b11c63668070383025d2fb07d4e56c5a64a","national_data_update_url_text":"2020-11-22: see changes on GitHub","national_data_update_url":"https://github.com/brockfanning/sdg-data-kazstat-upgrade/commit/91dec4745c9fbdb7720e2d8d1baa477c2b26c07f","is_global_indicator":true,"indicator":"3.5.1"}